[{"word": "This", "norm": "this", "start": 0.0, "end": 1.92}, {"word": "government", "norm": "government", "start": 1.92, "end": 3.16}, {"word": "is", "norm": "is", "start": 3.16, "end": 5.56}, {"word": "worse", "norm": "worse", "start": 8.63, "end": 9.07}, {"word": "than", "norm": "than", "start": 9.07, "end": 10.25}, {"word": "the", "norm": "the", "start": 10.25, "end": 10.57}, {"word": "apartheid", "norm": "apartheid", "start": 10.57, "end": 10.99}, {"word": "government", "norm": "government", "start": 10.99, "end": 11.65}, {"word": "because", "norm": "because", "start": 11.65, "end": 13.15}, {"word": "it", "norm": "it", "start": 13.15, "end": 13.53}, {"word": "wished", "norm": "wished", "start": 13.53, "end": 13.77}, {"word": "you", "norm": "you", "start": 13.77, "end": 13.99}, {"word": "were", "norm": "were", "start": 13.99, "end": 14.17}, {"word": "expecting", "norm": "expecting", "start": 14.17, "end": 14.59}, {"word": "it", "norm": "it", "start": 14.59, "end": 15.37}, {"word": "with", "norm": "with", "start": 15.37, "end": 15.49}, {"word": "the", "norm": "the", "start": 15.49, "end": 15.67}, {"word": "apartheid", "norm": "apartheid", "start": 15.67, "end": 15.99}, {"word": "government.", "norm": "government", "start": 15.99, "end": 16.71}, {"word": "Our", "norm": "our", "start": 17.71, "end": 17.93}, {"word": "government", "norm": "government", "start": 17.93, "end": 18.45}, {"word": "we", "norm": "we", "start": 18.45, "end": 18.69}, {"word": "were", "norm": "were", "start": 18.69, "end": 18.91}, {"word": "expecting", "norm": "expecting", "start": 18.91, "end": 19.37}, {"word": "that", "norm": "that", "start": 19.37, "end": 20.23}, {"word": "now", "norm": "now", "start": 20.23, "end": 21.19}, {"word": "we", "norm": "we", "start": 21.19, "end": 21.51}, {"word": "would", "norm": "would", "start": 21.51, "end": 21.91}, {"word": "have", "norm": "have", "start": 21.91, "end": 22.41}, {"word": "a", "norm": "a", "start": 22.41, "end": 22.91}, {"word": "government", "norm": "government", "start": 22.91, "end": 23.45}, {"word": "that", "norm": "that", "start": 23.45, "end": 24.61}, {"word": "was", "norm": "was", "start": 24.61, "end": 26.35}, {"word": "sensitive", "norm": "sensitive", "start": 26.35, "end": 28.13}, {"word": "to", "norm": "to", "start": 28.13, "end": 29.55}, {"word": "the", "norm": "the", "start": 29.55, "end": 29.71}, {"word": "sentiments", "norm": "sentiments", "start": 29.71, "end": 30.23}, {"word": "of", "norm": "of", "start": 30.23, "end": 30.71}, {"word": "our", "norm": "our", "start": 30.71, "end": 31.19}, {"word": "constitution.", "norm": "constitution", "start": 31.19, "end": 31.83}, {"word": "I,", "norm": "i", "start": 31.83, "end": 33.15}, {"word": "the", "norm": "the", "start": 39.48, "end": 40.16}, {"word": "trouble,", "norm": "trouble", "start": 40.16, "end": 40.72}, {"word": "I", "norm": "i", "start": 41.2, "end": 41.24}, {"word": "think", "norm": "think", "start": 41.24, "end": 41.56}, {"word": "I", "norm": "i", "start": 41.56, "end": 41.64}, {"word": "mean", "norm": "mean", "start": 41.64, "end": 41.82}, {"word": "one", "norm": "one", "start": 41.82, "end": 42.08}, {"word": "of", "norm": "of", "start": 42.08, "end": 42.32}, {"word": "big", "norm": "big", "start": 42.32, "end": 42.56}, {"word": "troubles", "norm": "troubles", "start": 42.56, "end": 43.0}, {"word": "is", "norm": "is", "start": 43.0, "end": 43.68}, {"word": "that", "norm": "that", "start": 43.68, "end": 44.34}, {"word": "the", "norm": "the", "start": 44.34, "end": 44.86}, {"word": "ANC", "norm": "anc", "start": 44.86, "end": 45.64}, {"word": "on", "norm": "on", "start": 45.64, "end": 46.22}, {"word": "the", "norm": "the", "start": 46.22, "end": 46.68}, {"word": "whole,", "norm": "whole", "start": 46.68, "end": 47.36}, {"word": "records", "norm": "records", "start": 47.78, "end": 48.4}, {"word": "that", "norm": "that", "start": 48.4, "end": 49.76}, {"word": "the", "norm": "the", "start": 49.76, "end": 50.76}, {"word": "freedom", "norm": "freedom", "start": 50.76, "end": 51.82}, {"word": "that", "norm": "that", "start": 51.82, "end": 52.28}, {"word": "we", "norm": "we", "start": 52.28, "end": 52.52}, {"word": "enjoy", "norm": "enjoy", "start": 52.52, "end": 53.0}, {"word": "is", "norm": "is", "start": 53.0, "end": 53.58}, {"word": "due", "norm": "due", "start": 53.58, "end": 53.82}, {"word": "to", "norm": "to", "start": 53.82, "end": 54.08}, {"word": "them.", "norm": "them", "start": 54.08, "end": 54.8}, {"word": "That", "norm": "that", "start": 56.14, "end": 56.48}, {"word": "is", "norm": "is", "start": 56.48, "end": 56.76}, {"word": "what", "norm": "what", "start": 56.76, "end": 57.02}, {"word": "they,", "norm": "they", "start": 57.02, "end": 57.64}, {"word": "they", "norm": "they", "start": 57.64, "end": 57.66}, {"word": "record", "norm": "record", "start": 57.66, "end": 58.0}, {"word": "that", "norm": "that", "start": 58.0, "end": 59.22}, {"word": "everybody", "norm": "everybody", "start": 59.22, "end": 60.12}, {"word": "else", "norm": "else", "start": 60.12, "end": 61.08}, {"word": "is", "norm": "is", "start": 61.08, "end": 61.62}, {"word": "just", "norm": "just", "start": 61.62, "end": 61.9}, {"word": "a", "norm": "a", "start": 61.9, "end": 62.16}, {"word": "sideline.", "norm": "sideline", "start": 62.16, "end": 62.72}, {"word": "Now", "norm": "now", "start": 62.72, "end": 63.3}, {"word": "there", "norm": "there", "start": 63.3, "end": 63.48}, {"word": "was", "norm": "was", "start": 63.48, "end": 63.68}, {"word": "a", "norm": "a", "start": 63.68, "end": 64.0}, {"word": "time", "norm": "time", "start": 64.0, "end": 64.74}, {"word": "when", "norm": "when", "start": 64.74, "end": 66.88}, {"word": "the", "norm": "the", "start": 66.88, "end": 67.86}, {"word": "people", "norm": "people", "start": 67.86, "end": 68.2}, {"word": "who", "norm": "who", "start": 68.2, "end": 68.42}, {"word": "were", "norm": "were", "start": 68.42, "end": 68.5}, {"word": "leading", "norm": "leading", "start": 68.5, "end": 68.7}, {"word": "this", "norm": "this", "start": 68.7, "end": 69.06}, {"word": "struggle", "norm": "struggle", "start": 69.06, "end": 69.56}, {"word": "were", "norm": "were", "start": 69.56, "end": 70.98}, {"word": "religious", "norm": "religious", "start": 70.98, "end": 71.34}, {"word": "leaders.", "norm": "leaders", "start": 71.34, "end": 71.98}, {"word": "I", "norm": "i", "start": 75.88, "end": 75.88}, {"word": "said", "norm": "said", "start": 75.88, "end": 76.22}, {"word": "in", "norm": "in", "start": 76.22, "end": 76.5}, {"word": "Parliament", "norm": "parliament", "start": 76.5, "end": 77.1}, {"word": "when", "norm": "when", "start": 77.1, "end": 78.34}, {"word": "this", "norm": "this", "start": 78.34, "end": 78.82}, {"word": "president", "norm": "president", "start": 78.82, "end": 79.26}, {"word": "of", "norm": "of", "start": 79.26, "end": 79.56}, {"word": "ours", "norm": "ours", "start": 79.56, "end": 80.22}, {"word": "was", "norm": "was", "start": 80.22, "end": 80.96}, {"word": "giving", "norm": "giving", "start": 80.96, "end": 81.32}, {"word": "his", "norm": "his", "start": 81.32, "end": 82.04}, {"word": "stake", "norm": "stake", "start": 82.04, "end": 82.92}, {"word": "of", "norm": "of", "start": 82.92, "end": 83.18}, {"word": "the", "norm": "the", "start": 83.18, "end": 83.44}, {"word": "nation", "norm": "nation", "start": 83.44, "end": 83.7}, {"word": "address.", "norm": "address", "start": 83.7, "end": 84.66}, {"word": "This", "norm": "this", "start": 84.66, "end": 85.8}, {"word": "President,", "norm": "president", "start": 85.8, "end": 86.52}, {"word": "I", "norm": "i", "start": 88.04, "end": 88.22}, {"word": "am", "norm": "am", "start": 88.22, "end": 88.28}, {"word": "sitting", "norm": "sitting", "start": 88.28, "end": 88.68}, {"word": "in", "norm": "in", "start": 88.68, "end": 89.8}, {"word": "the", "norm": "the", "start": 89.8, "end": 90.08}, {"word": "audience.", "norm": "audience", "start": 90.08, "end": 90.8}, {"word": "I", "norm": "i", "start": 91.92, "end": 92.12}, {"word": "listen", "norm": "listen", "start": 92.12, "end": 92.68}, {"word": "to", "norm": "to", "start": 92.68, "end": 93.4}, {"word": "this", "norm": "this", "start": 93.4, "end": 93.7}, {"word": "President", "norm": "president", "start": 93.7, "end": 94.44}, {"word": "telling,", "norm": "telling", "start": 94.44, "end": 96.64}, {"word": "I", "norm": "i", "start": 96.74, "end": 97.26}, {"word": "mean,", "norm": "mean", "start": 97.26, "end": 97.52}, {"word": "because", "norm": "because", "start": 97.56, "end": 97.78}, {"word": "paying", "norm": "paying", "start": 97.78, "end": 98.26}, {"word": "tribute", "norm": "tribute", "start": 98.26, "end": 99.1}, {"word": "to", "norm": "to", "start": 99.1, "end": 99.98}, {"word": "all", "norm": "all", "start": 99.98, "end": 100.42}, {"word": "kind", "norm": "kind", "start": 100.42, "end": 101.36}, {"word": "of", "norm": "of", "start": 101.36, "end": 101.58}, {"word": "people", "norm": "people", "start": 101.58, "end": 102.1}, {"word": "who", "norm": "who", "start": 104.1, "end": 104.6}, {"word": "had", "norm": "had", "start": 104.6, "end": 104.94}, {"word": "helped", "norm": "helped", "start": 104.94, "end": 105.82}, {"word": "in", "norm": "in", "start": 105.82, "end": 106.86}, {"word": "helping,", "norm": "helping", "start": 106.86, "end": 107.14}, {"word": "in", "norm": "in", "start": 107.62, "end": 107.62}, {"word": "bringing", "norm": "bringing", "start": 107.62, "end": 108.0}, {"word": "about", "norm": "about", "start": 108.0, "end": 109.52}, {"word": "democracy", "norm": "democracy", "start": 109.52, "end": 109.96}, {"word": "in", "norm": "in", "start": 109.96, "end": 110.26}, {"word": "this", "norm": "this", "start": 110.26, "end": 110.4}, {"word": "country.", "norm": "country", "start": 110.4, "end": 110.9}, {"word": "This", "norm": "this", "start": 110.9, "end": 112.68}, {"word": "president", "norm": "president", "start": 112.68, "end": 113.42}, {"word": "did", "norm": "did", "start": 115.28, "end": 116.3}, {"word": "mention", "norm": "mention", "start": 116.3, "end": 116.8}, {"word": "a", "norm": "a", "start": 116.8, "end": 117.26}, {"word": "single", "norm": "single", "start": 117.26, "end": 117.92}, {"word": "religious", "norm": "religious", "start": 117.92, "end": 118.9}, {"word": "leader,", "norm": "leader", "start": 118.9, "end": 119.86}, {"word": "1989,", "norm": "1989", "start": 121.84, "end": 123.04}, {"word": "religious", "norm": "religious", "start": 125.22, "end": 125.76}, {"word": "leaders,", "norm": "leaders", "start": 125.76, "end": 126.7}, {"word": "said", "norm": "said", "start": 127.92, "end": 128.18}, {"word": "to", "norm": "to", "start": 128.18, "end": 128.4}, {"word": "the", "norm": "the", "start": 128.4, "end": 128.48}, {"word": "people", "norm": "people", "start": 128.48, "end": 128.74}, {"word": "of", "norm": "of", "start": 128.74, "end": 129.04}, {"word": "Cape", "norm": "cape", "start": 129.04, "end": 129.26}, {"word": "Town", "norm": "town", "start": 129.26, "end": 129.88}, {"word": "with", "norm": "with", "start": 129.88, "end": 130.92}, {"word": "very", "norm": "very", "start": 130.92, "end": 131.16}, {"word": "enough.", "norm": "enough", "start": 131.16, "end": 132.78}, {"word": "It", "norm": "it", "start": 133.3, "end": 133.66}, {"word": "was", "norm": "was", "start": 133.66, "end": 134.0}, {"word": "religious", "norm": "religious", "start": 134.0, "end": 134.68}, {"word": "leaders", "norm": "leaders", "start": 134.68, "end": 135.84}, {"word": "who", "norm": "who", "start": 135.84, "end": 136.68}, {"word": "got", "norm": "got", "start": 136.68, "end": 137.4}, {"word": "30", "norm": "30", "start": 137.4, "end": 137.98}, {"word": ",000", "norm": "000", "start": 137.98, "end": 138.58}, {"word": "people", "norm": "people", "start": 138.58, "end": 139.74}, {"word": "to", "norm": "to", "start": 139.74, "end": 140.06}, {"word": "come", "norm": "come", "start": 140.06, "end": 140.28}, {"word": "to", "norm": "to", "start": 140.28, "end": 140.58}, {"word": "much.", "norm": "much", "start": 140.58, "end": 141.2}, {"word": "Let", "norm": "let", "start": 141.2, "end": 142.92}, {"word": "the", "norm": "the", "start": 142.92, "end": 143.28}, {"word": "ANC", "norm": "anc", "start": 143.28, "end": 143.98}, {"word": "know", "norm": "know", "start": 143.98, "end": 145.0}, {"word": "that", "norm": "that", "start": 145.0, "end": 146.32}, {"word": "they", "norm": "they", "start": 146.32, "end": 146.58}, {"word": "cannot", "norm": "cannot", "start": 146.58, "end": 147.14}, {"word": "ever", "norm": "ever", "start": 147.14, "end": 147.8}, {"word": "rush", "norm": "rush", "start": 147.8, "end": 148.44}, {"word": "us", "norm": "us", "start": 148.44, "end": 149.28}, {"word": "out.", "norm": "out", "start": 149.28, "end": 150.54}, {"word": "Let", "norm": "let", "start": 153.26, "end": 154.34}, {"word": "the", "norm": "the", "start": 154.34, "end": 154.8}, {"word": "ANC", "norm": "anc", "start": 154.8, "end": 156.62}, {"word": "know", "norm": "know", "start": 156.62, "end": 157.92}, {"word": "that", "norm": "that", "start": 162.04, "end": 162.74}, {"word": "they", "norm": "they", "start": 162.74, "end": 162.92}, {"word": "have", "norm": "have", "start": 162.92, "end": 164.78}, {"word": "a", "norm": "a", "start": 164.78, "end": 165.26}, {"word": "large", "norm": "large", "start": 165.26, "end": 166.06}, {"word": "majority.", "norm": "majority", "start": 166.06, "end": 167.06}, {"word": "Well,", "norm": "well", "start": 168.52, "end": 168.52}, {"word": "Mubarak", "norm": "mubarak", "start": 169.5, "end": 170.04}, {"word": "had", "norm": "had", "start": 170.04, "end": 170.36}, {"word": "a", "norm": "a", "start": 170.36, "end": 170.48}, {"word": "large", "norm": "large", "start": 170.48, "end": 170.7}, {"word": "majority.", "norm": "majority", "start": 170.7, "end": 171.24}, {"word": "Gaddafi", "norm": "gaddafi", "start": 172.56, "end": 173.84}, {"word": "had", "norm": "had", "start": 173.84, "end": 174.22}, {"word": "a", "norm": "a", "start": 174.22, "end": 174.4}, {"word": "large", "norm": "large", "start": 174.4, "end": 174.82}, {"word": "majority.", "norm": "majority", "start": 174.82, "end": 175.54}, {"word": "Watch", "norm": "watch", "start": 176.96, "end": 177.26}, {"word": "out,", "norm": "out", "start": 177.26, "end": 178.32}, {"word": "I", "norm": "i", "start": 179.28, "end": 179.6}, {"word": "am", "norm": "am", "start": 179.6, "end": 180.66}, {"word": "warning", "norm": "warning", "start": 180.66, "end": 181.24}, {"word": "you,", "norm": "you", "start": 181.24, "end": 182.76}, {"word": "watch", "norm": "watch", "start": 183.72, "end": 184.04}, {"word": "out,", "norm": "out", "start": 184.04, "end": 186.34}, {"word": "please", "norm": "please", "start": 190.34, "end": 190.94}, {"word": "watch", "norm": "watch", "start": 190.94, "end": 191.92}, {"word": "out.", "norm": "out", "start": 191.92, "end": 192.56}, {"word": "We", "norm": "we", "start": 193.34, "end": 194.12}, {"word": "were", "norm": "were", "start": 194.12, "end": 195.0}, {"word": "helped", "norm": "helped", "start": 195.0, "end": 195.5}, {"word": "by", "norm": "by", "start": 195.5, "end": 196.14}, {"word": "the", "norm": "the", "start": 196.14, "end": 196.42}, {"word": "international", "norm": "international", "start": 196.42, "end": 196.98}, {"word": "community", "norm": "community", "start": 196.98, "end": 197.82}, {"word": "to", "norm": "to", "start": 197.82, "end": 198.62}, {"word": "overcome", "norm": "overcome", "start": 198.62, "end": 199.1}, {"word": "a", "norm": "a", "start": 199.1, "end": 199.6}, {"word": "part", "norm": "part", "start": 199.6, "end": 199.84}, {"word": "of", "norm": "of", "start": 199.84, "end": 199.98}, {"word": "it.", "norm": "it", "start": 199.98, "end": 200.28}, {"word": "people", "norm": "people", "start": 200.28, "end": 202.38}, {"word": "were", "norm": "were", "start": 202.38, "end": 203.54}, {"word": "opposed", "norm": "opposed", "start": 203.54, "end": 204.2}, {"word": "to", "norm": "to", "start": 204.2, "end": 204.52}, {"word": "injustice", "norm": "injustice", "start": 204.52, "end": 205.02}, {"word": "and", "norm": "and", "start": 205.02, "end": 205.38}, {"word": "oppression", "norm": "oppression", "start": 205.38, "end": 205.84}, {"word": "and", "norm": "and", "start": 205.84, "end": 206.8}, {"word": "people", "norm": "people", "start": 206.8, "end": 207.16}, {"word": "believed", "norm": "believed", "start": 207.16, "end": 207.92}, {"word": "that", "norm": "that", "start": 207.92, "end": 208.64}, {"word": "we,", "norm": "we", "start": 208.64, "end": 209.0}, {"word": "South", "norm": "south", "start": 209.22, "end": 209.46}, {"word": "Africans,", "norm": "africans", "start": 209.46, "end": 210.06}, {"word": "would", "norm": "would", "start": 211.34, "end": 211.34}, {"word": "automatically", "norm": "automatically", "start": 211.34, "end": 211.9}, {"word": "be", "norm": "be", "start": 211.9, "end": 212.98}, {"word": "on", "norm": "on", "start": 212.98, "end": 213.12}, {"word": "the", "norm": "the", "start": 213.12, "end": 213.38}, {"word": "side", "norm": "side", "start": 213.38, "end": 213.92}, {"word": "of", "norm": "of", "start": 213.92, "end": 215.28}, {"word": "those", "norm": "those", "start": 215.28, "end": 215.78}, {"word": "who", "norm": "who", "start": 215.78, "end": 216.06}, {"word": "were", "norm": "were", "start": 216.06, "end": 216.14}, {"word": "being", "norm": "being", "start": 216.14, "end": 216.38}, {"word": "oppressed.", "norm": "oppressed", "start": 216.38, "end": 216.96}, {"word": "Tibet", "norm": "tibet", "start": 217.54, "end": 218.14}, {"word": "is", "norm": "is", "start": 218.14, "end": 218.82}, {"word": "being", "norm": "being", "start": 218.82, "end": 219.18}, {"word": "oppressed.", "norm": "oppressed", "start": 219.18, "end": 219.8}, {"word": "Our", "norm": "our", "start": 222.88, "end": 223.12}, {"word": "government", "norm": "government", "start": 223.12, "end": 223.74}, {"word": "representing", "norm": "representing", "start": 223.74, "end": 224.9}, {"word": "me,", "norm": "me", "start": 224.9, "end": 227.06}, {"word": "representing", "norm": "representing", "start": 227.34, "end": 227.78}, {"word": "me,", "norm": "me", "start": 227.78, "end": 228.9}, {"word": "says", "norm": "says", "start": 230.5, "end": 231.0}, {"word": "it", "norm": "it", "start": 231.0, "end": 231.72}, {"word": "will", "norm": "will", "start": 231.72, "end": 231.96}, {"word": "not", "norm": "not", "start": 231.96, "end": 232.46}, {"word": "support", "norm": "support", "start": 232.46, "end": 233.12}, {"word": "to", "norm": "to", "start": 233.12, "end": 233.92}, {"word": "burdens", "norm": "burdens", "start": 233.92, "end": 234.66}, {"word": "who", "norm": "who", "start": 234.66, "end": 235.9}, {"word": "are", "norm": "are", "start": 235.9, "end": 236.24}, {"word": "being", "norm": "being", "start": 236.24, "end": 236.66}, {"word": "oppressed", "norm": "oppressed", "start": 236.66, "end": 237.36}, {"word": "viciously", "norm": "viciously", "start": 237.36, "end": 239.48}, {"word": "by", "norm": "by", "start": 239.48, "end": 240.48}, {"word": "the", "norm": "the", "start": 240.48, "end": 240.62}, {"word": "Chinese.", "norm": "chinese", "start": 240.62, "end": 241.2}, {"word": "Hey,", "norm": "hey", "start": 244.3, "end": 244.3}, {"word": "Mr.", "norm": "mr", "start": 245.02, "end": 245.48}, {"word": "Ruma,", "norm": "ruma", "start": 246.82, "end": 248.1}, {"word": "you", "norm": "you", "start": 249.38, "end": 249.98}, {"word": "and", "norm": "and", "start": 249.98, "end": 250.48}, {"word": "your", "norm": "your", "start": 250.48, "end": 250.78}, {"word": "government", "norm": "government", "start": 250.78, "end": 251.5}, {"word": "don't", "norm": "dont", "start": 251.5, "end": 252.82}, {"word": "represent", "norm": "represent", "start": 252.82, "end": 253.52}, {"word": "me.", "norm": "me", "start": 253.52, "end": 254.6}, {"word": "You", "norm": "you", "start": 257.68, "end": 257.76}, {"word": "represent", "norm": "represent", "start": 257.76, "end": 258.32}, {"word": "your", "norm": "your", "start": 258.32, "end": 259.1}, {"word": "own", "norm": "own", "start": 259.1, "end": 259.52}, {"word": "interests.", "norm": "interests", "start": 259.52, "end": 260.12}, {"word": "And", "norm": "and", "start": 260.66, "end": 260.92}, {"word": "I'm", "norm": "im", "start": 260.92, "end": 261.34}, {"word": "warning", "norm": "warning", "start": 261.34, "end": 261.64}, {"word": "you.", "norm": "you", "start": 261.64, "end": 262.12}, {"word": "I", "norm": "i", "start": 262.12, "end": 262.36}, {"word": "really", "norm": "really", "start": 262.36, "end": 262.68}, {"word": "am", "norm": "am", "start": 262.68, "end": 263.04}, {"word": "warning", "norm": "warning", "start": 263.04, "end": 263.44}, {"word": "out", "norm": "out", "start": 263.44, "end": 264.16}, {"word": "of", "norm": "of", "start": 264.16, "end": 264.6}, {"word": "love.", "norm": "love", "start": 264.6, "end": 265.26}, {"word": "I", "norm": "i", "start": 266.56, "end": 266.76}, {"word": "am", "norm": "am", "start": 266.76, "end": 267.06}, {"word": "warning", "norm": "warning", "start": 267.06, "end": 267.3}, {"word": "you", "norm": "you", "start": 267.3, "end": 267.68}, {"word": "like", "norm": "like", "start": 267.68, "end": 268.12}, {"word": "I", "norm": "i", "start": 268.12, "end": 268.38}, {"word": "want", "norm": "want", "start": 268.38, "end": 268.86}, {"word": "the", "norm": "the", "start": 268.86, "end": 269.46}, {"word": "nationalists.", "norm": "nationalists", "start": 269.46, "end": 270.9}, {"word": "I", "norm": "i", "start": 271.98, "end": 271.98}, {"word": "am", "norm": "am", "start": 271.98, "end": 272.26}, {"word": "warning", "norm": "warning", "start": 272.26, "end": 272.52}, {"word": "you", "norm": "you", "start": 272.52, "end": 273.28}, {"word": "one", "norm": "one", "start": 274.75, "end": 275.29}, {"word": "day", "norm": "day", "start": 275.29, "end": 275.85}, {"word": "we", "norm": "we", "start": 275.85, "end": 276.49}, {"word": "will", "norm": "will", "start": 276.49, "end": 276.73}, {"word": "start", "norm": "start", "start": 276.73, "end": 276.99}, {"word": "praying", "norm": "praying", "start": 276.99, "end": 278.15}, {"word": "for", "norm": "for", "start": 278.7, "end": 279.21}, {"word": "the", "norm": "the", "start": 279.21, "end": 279.39}, {"word": "defeat", "norm": "defeat", "start": 279.39, "end": 280.01}, {"word": "of", "norm": "of", "start": 280.01, "end": 280.75}, {"word": "the", "norm": "the", "start": 280.75, "end": 280.97}, {"word": "ANC", "norm": "anc", "start": 280.97, "end": 281.53}, {"word": "government.", "norm": "government", "start": 281.53, "end": 282.53}, {"word": "You", "norm": "you", "start": 283.89, "end": 284.13}, {"word": "are", "norm": "are", "start": 284.13, "end": 285.09}, {"word": "disgraceful.", "norm": "disgraceful", "start": 285.09, "end": 286.99}, {"word": "I", "norm": "i", "start": 288.25, "end": 288.25}, {"word": "want", "norm": "want", "start": 288.25, "end": 288.65}, {"word": "to", "norm": "to", "start": 288.65, "end": 288.91}, {"word": "warn", "norm": "warn", "start": 288.91, "end": 289.13}, {"word": "you.", "norm": "you", "start": 289.13, "end": 290.19}, {"word": "You", "norm": "you", "start": 290.19, "end": 290.67}, {"word": "are", "norm": "are", "start": 290.67, "end": 291.09}, {"word": "behaving", "norm": "behaving", "start": 291.09, "end": 291.71}, {"word": "in", "norm": "in", "start": 291.71, "end": 292.51}, {"word": "a", "norm": "a", "start": 292.51, "end": 292.89}, {"word": "way", "norm": "way", "start": 292.89, "end": 293.29}, {"word": "that", "norm": "that", "start": 293.29, "end": 293.61}, {"word": "is", "norm": "is", "start": 293.61, "end": 294.07}, {"word": "totally", "norm": "totally", "start": 294.07, "end": 294.67}, {"word": "at", "norm": "at", "start": 294.67, "end": 295.59}, {"word": "variance", "norm": "variance", "start": 295.59, "end": 296.33}, {"word": "with", "norm": "with", "start": 296.33, "end": 297.11}, {"word": "the", "norm": "the", "start": 297.11, "end": 297.35}, {"word": "things", "norm": "things", "start": 297.35, "end": 297.79}, {"word": "for", "norm": "for", "start": 297.79, "end": 298.27}, {"word": "which", "norm": "which", "start": 298.27, "end": 298.51}, {"word": "we", "norm": "we", "start": 298.51, "end": 298.79}, {"word": "stood.", "norm": "stood", "start": 298.79, "end": 299.21}, {"word": "I", "norm": "i", "start": 300.49, "end": 300.69}, {"word": "am", "norm": "am", "start": 300.69, "end": 301.03}, {"word": "warning", "norm": "warning", "start": 301.03, "end": 301.31}, {"word": "you.", "norm": "you", "start": 301.31, "end": 302.87}, {"word": "I", "norm": "i", "start": 303.45, "end": 303.61}, {"word": "am", "norm": "am", "start": 303.61, "end": 304.03}, {"word": "warning", "norm": "warning", "start": 304.03, "end": 304.33}, {"word": "you", "norm": "you", "start": 304.33, "end": 305.77}, {"word": "that", "norm": "that", "start": 305.77, "end": 306.51}, {"word": "we", "norm": "we", "start": 306.51, "end": 306.95}, {"word": "will", "norm": "will", "start": 306.95, "end": 307.45}, {"word": "pray", "norm": "pray", "start": 307.45, "end": 307.97}, {"word": "and", "norm": "and", "start": 307.97, "end": 308.57}, {"word": "repraise", "norm": "repraise", "start": 308.57, "end": 309.29}, {"word": "for", "norm": "for", "start": 309.29, "end": 309.75}, {"word": "the", "norm": "the", "start": 309.75, "end": 309.93}, {"word": "downfall", "norm": "downfall", "start": 309.93, "end": 310.67}, {"word": "of", "norm": "of", "start": 310.67, "end": 311.07}, {"word": "the", "norm": "the", "start": 311.07, "end": 311.23}, {"word": "apartment.", "norm": "apartment", "start": 311.23, "end": 311.67}, {"word": "We", "norm": "we", "start": 311.85, "end": 312.35}, {"word": "will", "norm": "will", "start": 312.35, "end": 312.67}, {"word": "pray", "norm": "pray", "start": 312.67, "end": 313.15}, {"word": "for", "norm": "for", "start": 313.15, "end": 313.65}, {"word": "the", "norm": "the", "start": 313.65, "end": 313.97}, {"word": "downfall", "norm": "downfall", "start": 313.97, "end": 314.55}, {"word": "of", "norm": "of", "start": 314.55, "end": 314.89}, {"word": "a", "norm": "a", "start": 314.89, "end": 315.17}, {"word": "government", "norm": "government", "start": 315.17, "end": 315.67}, {"word": "that", "norm": "that", "start": 315.67, "end": 316.47}, {"word": "misrepresent", "norm": "misrepresent", "start": 316.47, "end": 317.81}, {"word": "us.", "norm": "us", "start": 317.81, "end": 318.57}, {"word": "You", "norm": "you", "start": 318.57, "end": 319.49}, {"word": "have", "norm": "have", "start": 319.49, "end": 319.89}, {"word": "got", "norm": "got", "start": 319.89, "end": 321.27}, {"word": "a", "norm": "a", "start": 321.27, "end": 321.79}, {"word": "huge", "norm": "huge", "start": 321.79, "end": 322.37}, {"word": "majority.", "norm": "majority", "start": 322.37, "end": 323.33}, {"word": "That's", "norm": "thats", "start": 324.49, "end": 324.67}, {"word": "nothing.", "norm": "nothing", "start": 324.67, "end": 324.99}, {"word": "The", "norm": "the", "start": 326.99, "end": 327.09}, {"word": "Nationalists", "norm": "nationalists", "start": 327.09, "end": 328.29}, {"word": "had", "norm": "had", "start": 328.29, "end": 328.91}, {"word": "a", "norm": "a", "start": 328.91, "end": 329.29}, {"word": "huge", "norm": "huge", "start": 329.29, "end": 329.65}, {"word": "majority", "norm": "majority", "start": 329.65, "end": 330.23}, {"word": "that", "norm": "that", "start": 330.23, "end": 331.73}, {"word": "was", "norm": "was", "start": 331.73, "end": 332.07}, {"word": "increasing", "norm": "increasing", "start": 332.07, "end": 332.63}, {"word": "the", "norm": "the", "start": 334.16, "end": 335.54}, {"word": "bit,", "norm": "bit", "start": 335.54, "end": 336.02}, {"word": "the", "norm": "the", "start": 336.5, "end": 336.74}, {"word": "dust.", "norm": "dust", "start": 336.74, "end": 337.24}, {"word": "Wash", "norm": "wash", "start": 338.46, "end": 338.72}, {"word": "out", "norm": "out", "start": 338.72, "end": 339.88}, {"word": "in", "norm": "in", "start": 339.88, "end": 340.44}, {"word": "the", "norm": "the", "start": 340.44, "end": 340.78}, {"word": "government,", "norm": "government", "start": 340.78, "end": 341.24}, {"word": "wash", "norm": "wash", "start": 342.28, "end": 342.46}, {"word": "out.", "norm": "out", "start": 342.46, "end": 343.22}]